{
  "title": "Schronisko PTTK na Klimczoku",
  "mountains": "Karpaty, Beskid Śląski",
  "height": "1034",
  "latitude": "49.7385790",
  "longitude": "19.0049904",
  "description": "Schronisko PTTK na Klimczoku to nazwa powszechnie używana, chociaż w rzeczywistości schronisko położone jest trochę poniżej szczytu Magury i od rzeczywistego szczytu Klimczoka oddzielone jest przełęczą Siodło.Jest bardzo popularne w Beskidzie Śląskim ze względu na niewielką odległość kolejki gondolowej na pobliski szczyt Szyndzielni. w otoczeniu schroniska znajduje się gęsta sieć szlaków turystycznych – między innymi do Schroniska PTTK na Błatniej i do Chaty Wuja Toma na Przełęczy Karkoszczonka. Przy obiekcie jest boisko do siatkówki, miejsce na grill i ognisko, plac zabaw dla dzieci. Zimą jest możliwość organizowania kuligów, a latem przejażdżek samochodem terenowym. W sąsiedztwie schroniska jest wyciąg narciarski. W pobliżu schroniska przechodzą następujące szlaki: do Bystrej (szlak niebieski); do Szczyrku (szlak niebieski); do Brennej (szlak żółty, ok. 2 godz.); do Wapienicy (szlak żółty, 2 godz.30 min.); do Bielska-Białej (szlak czerwony, 2 godz. 30 min.)."
}